{
  "id": "0",
  "name": "gonza-go-db",
  "createdAt": "2025-03-13T21:56:18.409Z",
  "updatedAt": "2025-06-15T19:37:17.299Z",
  "databaseType": "mariadb",
  "tables": [
    {
      "id": "1",
      "name": "suppliers",
      "x": 41.370993104785924,
      "y": -387.5656151320689,
      "fields": [
        {
          "id": "2",
          "name": "id",
          "type": {
            "id": "bigint",
            "name": "bigint"
          },
          "unique": true,
          "nullable": false,
          "primaryKey": true,
          "createdAt": 1744990053253
        },
        {
          "id": "3",
          "name": "name",
          "type": {
            "id": "varchar",
            "name": "varchar"
          },
          "unique": false,
          "nullable": false,
          "primaryKey": false,
          "createdAt": 1744990125077
        },
        {
          "id": "4",
          "name": "state",
          "type": {
            "id": "boolean",
            "name": "boolean"
          },
          "unique": false,
          "nullable": false,
          "primaryKey": false,
          "createdAt": 1744990331867
        },
        {
          "id": "5",
          "name": "description",
          "type": {
            "id": "varchar",
            "name": "varchar"
          },
          "unique": false,
          "nullable": true,
          "primaryKey": false,
          "createdAt": 1744990545887
        },
        {
          "id": "6",
          "name": "created_by",
          "type": {
            "id": "bigint",
            "name": "bigint"
          },
          "unique": false,
          "nullable": false,
          "primaryKey": false,
          "createdAt": 1744990456823
        },
        {
          "id": "7",
          "name": "created_at",
          "type": {
            "id": "timestamp",
            "name": "timestamp"
          },
          "unique": false,
          "nullable": false,
          "primaryKey": false,
          "createdAt": 1744990400899
        },
        {
          "id": "8",
          "name": "updated_at",
          "type": {
            "id": "datetime",
            "name": "datetime"
          },
          "unique": false,
          "nullable": false,
          "primaryKey": false,
          "createdAt": 1744990512536
        }
      ],
      "indexes": [],
      "color": "#8a61f5",
      "createdAt": 1744990053253,
      "isView": false,
      "order": 20,
      "diagramId": "iwgpq31e7w5c"
    },
    {
      "id": "9",
      "name": "brands",
      "x": 907.3185481987678,
      "y": 229.51129034228276,
      "fields": [
        {
          "id": "10",
          "name": "id",
          "type": {
            "id": "bigint",
            "name": "bigint"
          },
          "unique": true,
          "nullable": false,
          "primaryKey": true,
          "createdAt": 1750014199249
        },
        {
          "id": "11",
          "name": "name",
          "type": {
            "id": "text",
            "name": "text"
          },
          "unique": true,
          "nullable": false,
          "primaryKey": false,
          "createdAt": 1750014243625
        },
        {
          "id": "12",
          "name": "created_by",
          "type": {
            "id": "bigint",
            "name": "bigint"
          },
          "unique": false,
          "nullable": true,
          "primaryKey": false,
          "createdAt": 1750014263384
        }
      ],
      "indexes": [],
      "color": "#7175fa",
      "createdAt": 1750014199250,
      "isView": false,
      "order": 26,
      "diagramId": "iwgpq31e7w5c"
    },
    {
      "id": "13",
      "name": "failed_jobs",
      "schema": "gonza-go",
      "x": 115.00555951532431,
      "y": 602.3156094084102,
      "fields": [
        {
          "id": "14",
          "name": "id",
          "type": {
            "id": "bigint",
            "name": "bigint"
          },
          "primaryKey": true,
          "unique": true,
          "nullable": false,
          "createdAt": 1741902978200
        },
        {
          "id": "15",
          "name": "uuid",
          "type": {
            "id": "varchar",
            "name": "varchar"
          },
          "primaryKey": false,
          "unique": true,
          "nullable": false,
          "characterMaximumLength": "255",
          "collation": "utf8mb4_unicode_ci",
          "createdAt": 1741902978200
        },
        {
          "id": "16",
          "name": "connection",
          "type": {
            "id": "text",
            "name": "text"
          },
          "primaryKey": false,
          "unique": false,
          "nullable": false,
          "characterMaximumLength": "65535",
          "collation": "utf8mb4_unicode_ci",
          "createdAt": 1741902978200
        },
        {
          "id": "17",
          "name": "queue",
          "type": {
            "id": "text",
            "name": "text"
          },
          "primaryKey": false,
          "unique": false,
          "nullable": false,
          "characterMaximumLength": "65535",
          "collation": "utf8mb4_unicode_ci",
          "createdAt": 1741902978200
        },
        {
          "id": "18",
          "name": "payload",
          "type": {
            "id": "longtext",
            "name": "longtext"
          },
          "primaryKey": false,
          "unique": false,
          "nullable": false,
          "characterMaximumLength": "4294967295",
          "collation": "utf8mb4_unicode_ci",
          "createdAt": 1741902978200
        },
        {
          "id": "19",
          "name": "exception",
          "type": {
            "id": "longtext",
            "name": "longtext"
          },
          "primaryKey": false,
          "unique": false,
          "nullable": false,
          "characterMaximumLength": "4294967295",
          "collation": "utf8mb4_unicode_ci",
          "createdAt": 1741902978200
        },
        {
          "id": "20",
          "name": "failed_at",
          "type": {
            "id": "timestamp",
            "name": "timestamp"
          },
          "primaryKey": false,
          "unique": false,
          "nullable": false,
          "default": "current_timestamp()",
          "createdAt": 1741902978200
        }
      ],
      "indexes": [
        {
          "id": "21",
          "name": "PRIMARY",
          "unique": true,
          "fieldIds": [
            "14"
          ],
          "createdAt": 1741902978200
        },
        {
          "id": "22",
          "name": "failed_jobs_uuid_unique",
          "unique": true,
          "fieldIds": [
            "15"
          ],
          "createdAt": 1741902978200
        }
      ],
      "color": "#8a61f5",
      "isView": false,
      "isMaterializedView": false,
      "createdAt": 1741902978200,
      "diagramId": "iwgpq31e7w5c"
    },
    {
      "id": "23",
      "name": "model_has_roles",
      "schema": "gonza-go",
      "x": 1307.5027797576622,
      "y": 769.9147540983607,
      "fields": [
        {
          "id": "24",
          "name": "role_id",
          "type": {
            "id": "bigint",
            "name": "bigint"
          },
          "primaryKey": true,
          "unique": false,
          "nullable": false,
          "createdAt": 1741902978200
        },
        {
          "id": "25",
          "name": "model_type",
          "type": {
            "id": "varchar",
            "name": "varchar"
          },
          "primaryKey": true,
          "unique": false,
          "nullable": false,
          "characterMaximumLength": "255",
          "collation": "utf8mb4_unicode_ci",
          "createdAt": 1741902978200
        },
        {
          "id": "26",
          "name": "model_id",
          "type": {
            "id": "bigint",
            "name": "bigint"
          },
          "primaryKey": true,
          "unique": false,
          "nullable": false,
          "createdAt": 1741902978200
        }
      ],
      "indexes": [
        {
          "id": "27",
          "name": "PRIMARY",
          "unique": true,
          "fieldIds": [
            "24",
            "26",
            "25"
          ],
          "createdAt": 1741902978200
        },
        {
          "id": "28",
          "name": "model_has_roles_model_id_model_type_index",
          "unique": false,
          "fieldIds": [
            "26",
            "25"
          ],
          "createdAt": 1741902978200
        }
      ],
      "color": "#9ef07a",
      "isView": false,
      "isMaterializedView": false,
      "createdAt": 1741902978200,
      "diagramId": "iwgpq31e7w5c"
    },
    {
      "id": "29",
      "name": "password_reset_tokens",
      "schema": "gonza-go",
      "x": 435.55628389317644,
      "y": 757.9534328596767,
      "fields": [
        {
          "id": "30",
          "name": "email",
          "type": {
            "id": "varchar",
            "name": "varchar"
          },
          "primaryKey": true,
          "unique": true,
          "nullable": false,
          "characterMaximumLength": "255",
          "collation": "utf8mb4_unicode_ci",
          "createdAt": 1741902978200
        },
        {
          "id": "31",
          "name": "token",
          "type": {
            "id": "varchar",
            "name": "varchar"
          },
          "primaryKey": false,
          "unique": false,
          "nullable": false,
          "characterMaximumLength": "255",
          "collation": "utf8mb4_unicode_ci",
          "createdAt": 1741902978200
        },
        {
          "id": "32",
          "name": "created_at",
          "type": {
            "id": "timestamp",
            "name": "timestamp"
          },
          "primaryKey": false,
          "unique": false,
          "nullable": true,
          "default": "NULL",
          "createdAt": 1741902978200
        }
      ],
      "indexes": [
        {
          "id": "33",
          "name": "PRIMARY",
          "unique": true,
          "fieldIds": [
            "30"
          ],
          "createdAt": 1741902978200
        }
      ],
      "color": "#b067e9",
      "isView": false,
      "isMaterializedView": false,
      "createdAt": 1741902978200,
      "diagramId": "iwgpq31e7w5c"
    },
    {
      "id": "34",
      "name": "cache",
      "schema": "gonza-go",
      "x": 913.0850080556854,
      "y": 1015.5488712060774,
      "fields": [
        {
          "id": "35",
          "name": "key",
          "type": {
            "id": "varchar",
            "name": "varchar"
          },
          "primaryKey": true,
          "unique": true,
          "nullable": false,
          "characterMaximumLength": "255",
          "collation": "utf8mb4_unicode_ci",
          "createdAt": 1741902978199
        },
        {
          "id": "36",
          "name": "value",
          "type": {
            "id": "mediumtext",
            "name": "mediumtext"
          },
          "primaryKey": false,
          "unique": false,
          "nullable": false,
          "characterMaximumLength": "16777215",
          "collation": "utf8mb4_unicode_ci",
          "createdAt": 1741902978199
        },
        {
          "id": "37",
          "name": "expiration",
          "type": {
            "id": "int",
            "name": "int"
          },
          "primaryKey": false,
          "unique": false,
          "nullable": false,
          "createdAt": 1741902978199
        }
      ],
      "indexes": [
        {
          "id": "38",
          "name": "PRIMARY",
          "unique": true,
          "fieldIds": [
            "35"
          ],
          "createdAt": 1741902978199
        }
      ],
      "color": "#8eb7ff",
      "isView": false,
      "isMaterializedView": false,
      "createdAt": 1741902978199,
      "diagramId": "iwgpq31e7w5c"
    },
    {
      "id": "39",
      "name": "migrations",
      "schema": "gonza-go",
      "x": 114.44960798289299,
      "y": 947.4434782608695,
      "fields": [
        {
          "id": "40",
          "name": "id",
          "type": {
            "id": "int",
            "name": "int"
          },
          "primaryKey": true,
          "unique": true,
          "nullable": false,
          "createdAt": 1741902978197
        },
        {
          "id": "41",
          "name": "migration",
          "type": {
            "id": "varchar",
            "name": "varchar"
          },
          "primaryKey": false,
          "unique": false,
          "nullable": false,
          "characterMaximumLength": "255",
          "collation": "utf8mb4_unicode_ci",
          "createdAt": 1741902978197
        },
        {
          "id": "42",
          "name": "batch",
          "type": {
            "id": "int",
            "name": "int"
          },
          "primaryKey": false,
          "unique": false,
          "nullable": false,
          "createdAt": 1741902978197
        }
      ],
      "indexes": [
        {
          "id": "43",
          "name": "PRIMARY",
          "unique": true,
          "fieldIds": [
            "40"
          ],
          "createdAt": 1741902978197
        }
      ],
      "color": "#b067e9",
      "isView": false,
      "isMaterializedView": false,
      "createdAt": 1741902978197,
      "diagramId": "iwgpq31e7w5c"
    },
    {
      "id": "44",
      "name": "permissions",
      "schema": "gonza-go",
      "x": 894.9981468282252,
      "y": 439.9592302209551,
      "fields": [
        {
          "id": "45",
          "name": "id",
          "type": {
            "id": "bigint",
            "name": "bigint"
          },
          "primaryKey": true,
          "unique": true,
          "nullable": false,
          "createdAt": 1741902978200
        },
        {
          "id": "46",
          "name": "name",
          "type": {
            "id": "varchar",
            "name": "varchar"
          },
          "primaryKey": false,
          "unique": false,
          "nullable": false,
          "characterMaximumLength": "255",
          "collation": "utf8mb4_unicode_ci",
          "createdAt": 1741902978200
        },
        {
          "id": "47",
          "name": "guard_name",
          "type": {
            "id": "varchar",
            "name": "varchar"
          },
          "primaryKey": false,
          "unique": false,
          "nullable": false,
          "characterMaximumLength": "255",
          "collation": "utf8mb4_unicode_ci",
          "createdAt": 1741902978200
        },
        {
          "id": "48",
          "name": "created_at",
          "type": {
            "id": "timestamp",
            "name": "timestamp"
          },
          "primaryKey": false,
          "unique": false,
          "nullable": true,
          "default": "NULL",
          "createdAt": 1741902978200
        },
        {
          "id": "49",
          "name": "updated_at",
          "type": {
            "id": "timestamp",
            "name": "timestamp"
          },
          "primaryKey": false,
          "unique": false,
          "nullable": true,
          "default": "NULL",
          "createdAt": 1741902978200
        }
      ],
      "indexes": [
        {
          "id": "50",
          "name": "PRIMARY",
          "unique": true,
          "fieldIds": [
            "45"
          ],
          "createdAt": 1741902978200
        },
        {
          "id": "51",
          "name": "permissions_name_guard_name_unique",
          "unique": true,
          "fieldIds": [
            "46",
            "47"
          ],
          "createdAt": 1741902978200
        }
      ],
      "color": "#7175fa",
      "isView": false,
      "isMaterializedView": false,
      "createdAt": 1741902978200,
      "diagramId": "iwgpq31e7w5c"
    },
    {
      "id": "52",
      "name": "orders",
      "x": 916.7130418156169,
      "y": -190.5498038714905,
      "fields": [
        {
          "id": "53",
          "name": "id",
          "type": {
            "id": "bigint",
            "name": "bigint"
          },
          "unique": true,
          "nullable": false,
          "primaryKey": true,
          "createdAt": 1741905148173
        },
        {
          "id": "54",
          "name": "user_id",
          "type": {
            "id": "bigint",
            "name": "bigint"
          },
          "unique": false,
          "nullable": false,
          "primaryKey": false,
          "createdAt": 1741905174812
        },
        {
          "id": "55",
          "name": "order_date",
          "type": {
            "id": "datetime",
            "name": "datetime"
          },
          "unique": false,
          "nullable": false,
          "primaryKey": false,
          "createdAt": 1741905317326
        },
        {
          "id": "56",
          "name": "total_amount",
          "type": {
            "id": "float",
            "name": "float"
          },
          "unique": false,
          "nullable": false,
          "primaryKey": false,
          "createdAt": 1741905368879
        },
        {
          "id": "57",
          "name": "status",
          "type": {
            "id": "enum",
            "name": "enum"
          },
          "unique": false,
          "nullable": false,
          "primaryKey": false,
          "createdAt": 1741905439668
        }
      ],
      "indexes": [],
      "color": "#4dee8a",
      "createdAt": 1741905148173,
      "isView": false,
      "order": 17,
      "diagramId": "iwgpq31e7w5c"
    },
    {
      "id": "58",
      "name": "supplier_contacts",
      "x": -343.57128955397576,
      "y": -419.7639467880768,
      "fields": [
        {
          "id": "59",
          "name": "id",
          "type": {
            "id": "bigint",
            "name": "bigint"
          },
          "unique": true,
          "nullable": false,
          "primaryKey": true,
          "createdAt": 1744991244203
        },
        {
          "id": "60",
          "name": "supplier_id",
          "type": {
            "id": "bigint",
            "name": "bigint"
          },
          "unique": false,
          "nullable": false,
          "primaryKey": false,
          "createdAt": 1744991266490
        },
        {
          "id": "61",
          "name": "name",
          "type": {
            "id": "varchar",
            "name": "varchar"
          },
          "unique": false,
          "nullable": false,
          "primaryKey": false,
          "createdAt": 1744991302057
        },
        {
          "id": "62",
          "name": "phone",
          "type": {
            "id": "varchar",
            "name": "varchar"
          },
          "unique": false,
          "nullable": false,
          "primaryKey": false,
          "createdAt": 1744991322266
        },
        {
          "id": "63",
          "name": "email",
          "type": {
            "id": "varchar",
            "name": "varchar"
          },
          "unique": false,
          "nullable": true,
          "primaryKey": false,
          "createdAt": 1744991308626
        }
      ],
      "indexes": [],
      "color": "#ff6363",
      "createdAt": 1744991244203,
      "isView": false,
      "order": 22,
      "diagramId": "iwgpq31e7w5c"
    },
    {
      "id": "64",
      "name": "product_brands",
      "x": 484.39408604198013,
      "y": 203.2419354954605,
      "fields": [
        {
          "id": "65",
          "name": "product_id",
          "type": {
            "id": "bigint",
            "name": "bigint"
          },
          "unique": true,
          "nullable": false,
          "primaryKey": true,
          "createdAt": 1750014369615
        },
        {
          "id": "66",
          "name": "brand_id",
          "type": {
            "id": "bigint",
            "name": "bigint"
          },
          "unique": false,
          "nullable": false,
          "primaryKey": false,
          "createdAt": 1750014435168
        }
      ],
      "indexes": [],
      "color": "#ff6363",
      "createdAt": 1750014369615,
      "isView": false,
      "order": 27,
      "diagramId": "iwgpq31e7w5c"
    },
    {
      "id": "67",
      "name": "categories",
      "x": 355.2815998516553,
      "y": 391.59465576007796,
      "fields": [
        {
          "id": "68",
          "name": "id",
          "type": {
            "id": "bigint",
            "name": "bigint"
          },
          "unique": true,
          "nullable": false,
          "primaryKey": true,
          "createdAt": 1741903049306
        },
        {
          "id": "69",
          "name": "name",
          "type": {
            "id": "varchar",
            "name": "varchar"
          },
          "unique": false,
          "nullable": false,
          "primaryKey": false,
          "createdAt": 1741903260473,
          "characterMaximumLength": "100"
        },
        {
          "id": "70",
          "name": "description",
          "type": {
            "id": "text",
            "name": "text"
          },
          "unique": false,
          "nullable": false,
          "primaryKey": false,
          "createdAt": 1741903510703
        }
      ],
      "indexes": [],
      "color": "#42e0c0",
      "createdAt": 1741903049306,
      "isView": false,
      "order": 15,
      "diagramId": "iwgpq31e7w5c"
    },
    {
      "id": "71",
      "name": "sessions",
      "schema": "gonza-go",
      "x": 1293.8008553100494,
      "y": 994.9610833927297,
      "fields": [
        {
          "id": "72",
          "name": "id",
          "type": {
            "id": "varchar",
            "name": "varchar"
          },
          "primaryKey": true,
          "unique": true,
          "nullable": false,
          "characterMaximumLength": "255",
          "collation": "utf8mb4_unicode_ci",
          "createdAt": 1741902978200
        },
        {
          "id": "73",
          "name": "user_id",
          "type": {
            "id": "bigint",
            "name": "bigint"
          },
          "primaryKey": false,
          "unique": false,
          "nullable": true,
          "default": "NULL",
          "createdAt": 1741902978200
        },
        {
          "id": "74",
          "name": "ip_address",
          "type": {
            "id": "varchar",
            "name": "varchar"
          },
          "primaryKey": false,
          "unique": false,
          "nullable": true,
          "characterMaximumLength": "45",
          "default": "NULL",
          "collation": "utf8mb4_unicode_ci",
          "createdAt": 1741902978200
        },
        {
          "id": "75",
          "name": "user_agent",
          "type": {
            "id": "text",
            "name": "text"
          },
          "primaryKey": false,
          "unique": false,
          "nullable": true,
          "characterMaximumLength": "65535",
          "default": "NULL",
          "collation": "utf8mb4_unicode_ci",
          "createdAt": 1741902978200
        },
        {
          "id": "76",
          "name": "payload",
          "type": {
            "id": "longtext",
            "name": "longtext"
          },
          "primaryKey": false,
          "unique": false,
          "nullable": false,
          "characterMaximumLength": "4294967295",
          "collation": "utf8mb4_unicode_ci",
          "createdAt": 1741902978200
        },
        {
          "id": "77",
          "name": "last_activity",
          "type": {
            "id": "int",
            "name": "int"
          },
          "primaryKey": false,
          "unique": false,
          "nullable": false,
          "createdAt": 1741902978200
        }
      ],
      "indexes": [
        {
          "id": "78",
          "name": "PRIMARY",
          "unique": true,
          "fieldIds": [
            "72"
          ],
          "createdAt": 1741902978200
        },
        {
          "id": "79",
          "name": "sessions_user_id_index",
          "unique": false,
          "fieldIds": [
            "73"
          ],
          "createdAt": 1741902978200
        },
        {
          "id": "80",
          "name": "sessions_last_activity_index",
          "unique": false,
          "fieldIds": [
            "77"
          ],
          "createdAt": 1741902978200
        }
      ],
      "color": "#b067e9",
      "isView": false,
      "isMaterializedView": false,
      "createdAt": 1741902978200,
      "diagramId": "iwgpq31e7w5c"
    },
    {
      "id": "81",
      "name": "role_has_permissions",
      "schema": "gonza-go",
      "x": 427.4731290092658,
      "y": 584.8461867426942,
      "fields": [
        {
          "id": "82",
          "name": "permission_id",
          "type": {
            "id": "bigint",
            "name": "bigint"
          },
          "primaryKey": true,
          "unique": false,
          "nullable": false,
          "createdAt": 1741902978200
        },
        {
          "id": "83",
          "name": "role_id",
          "type": {
            "id": "bigint",
            "name": "bigint"
          },
          "primaryKey": true,
          "unique": false,
          "nullable": false,
          "createdAt": 1741902978200
        }
      ],
      "indexes": [
        {
          "id": "84",
          "name": "PRIMARY",
          "unique": true,
          "fieldIds": [
            "82",
            "83"
          ],
          "createdAt": 1741902978200
        },
        {
          "id": "85",
          "name": "role_has_permissions_role_id_foreign",
          "unique": false,
          "fieldIds": [
            "83"
          ],
          "createdAt": 1741902978200
        }
      ],
      "color": "#8eb7ff",
      "isView": false,
      "isMaterializedView": false,
      "createdAt": 1741902978200,
      "diagramId": "iwgpq31e7w5c"
    },
    {
      "id": "86",
      "name": "roles",
      "schema": "gonza-go",
      "x": 900,
      "y": 719.8962223806129,
      "fields": [
        {
          "id": "87",
          "name": "id",
          "type": {
            "id": "bigint",
            "name": "bigint"
          },
          "primaryKey": true,
          "unique": true,
          "nullable": false,
          "createdAt": 1741902978200
        },
        {
          "id": "88",
          "name": "name",
          "type": {
            "id": "varchar",
            "name": "varchar"
          },
          "primaryKey": false,
          "unique": false,
          "nullable": false,
          "characterMaximumLength": "255",
          "collation": "utf8mb4_unicode_ci",
          "createdAt": 1741902978200
        },
        {
          "id": "89",
          "name": "guard_name",
          "type": {
            "id": "varchar",
            "name": "varchar"
          },
          "primaryKey": false,
          "unique": false,
          "nullable": false,
          "characterMaximumLength": "255",
          "collation": "utf8mb4_unicode_ci",
          "createdAt": 1741902978200
        },
        {
          "id": "90",
          "name": "created_at",
          "type": {
            "id": "timestamp",
            "name": "timestamp"
          },
          "primaryKey": false,
          "unique": false,
          "nullable": true,
          "default": "NULL",
          "createdAt": 1741902978201
        },
        {
          "id": "91",
          "name": "updated_at",
          "type": {
            "id": "timestamp",
            "name": "timestamp"
          },
          "primaryKey": false,
          "unique": false,
          "nullable": true,
          "default": "NULL",
          "createdAt": 1741902978201
        }
      ],
      "indexes": [
        {
          "id": "92",
          "name": "PRIMARY",
          "unique": true,
          "fieldIds": [
            "87"
          ],
          "createdAt": 1741902978201
        },
        {
          "id": "93",
          "name": "roles_name_guard_name_unique",
          "unique": true,
          "fieldIds": [
            "88",
            "89"
          ],
          "createdAt": 1741902978201
        }
      ],
      "color": "#7175fa",
      "isView": false,
      "isMaterializedView": false,
      "createdAt": 1741902978201,
      "diagramId": "iwgpq31e7w5c"
    },
    {
      "id": "94",
      "name": "jobs",
      "schema": "gonza-go",
      "x": 121.4307020000654,
      "y": 1133.873676382556,
      "fields": [
        {
          "id": "95",
          "name": "id",
          "type": {
            "id": "bigint",
            "name": "bigint"
          },
          "primaryKey": true,
          "unique": true,
          "nullable": false,
          "createdAt": 1741902978198
        },
        {
          "id": "96",
          "name": "queue",
          "type": {
            "id": "varchar",
            "name": "varchar"
          },
          "primaryKey": false,
          "unique": false,
          "nullable": false,
          "characterMaximumLength": "255",
          "collation": "utf8mb4_unicode_ci",
          "createdAt": 1741902978198
        },
        {
          "id": "97",
          "name": "payload",
          "type": {
            "id": "longtext",
            "name": "longtext"
          },
          "primaryKey": false,
          "unique": false,
          "nullable": false,
          "characterMaximumLength": "4294967295",
          "collation": "utf8mb4_unicode_ci",
          "createdAt": 1741902978198
        },
        {
          "id": "98",
          "name": "attempts",
          "type": {
            "id": "tinyint",
            "name": "tinyint"
          },
          "primaryKey": false,
          "unique": false,
          "nullable": false,
          "createdAt": 1741902978198
        },
        {
          "id": "99",
          "name": "reserved_at",
          "type": {
            "id": "int",
            "name": "int"
          },
          "primaryKey": false,
          "unique": false,
          "nullable": true,
          "default": "NULL",
          "createdAt": 1741902978198
        },
        {
          "id": "100",
          "name": "available_at",
          "type": {
            "id": "int",
            "name": "int"
          },
          "primaryKey": false,
          "unique": false,
          "nullable": false,
          "createdAt": 1741902978198
        },
        {
          "id": "101",
          "name": "created_at",
          "type": {
            "id": "int",
            "name": "int"
          },
          "primaryKey": false,
          "unique": false,
          "nullable": false,
          "createdAt": 1741902978198
        }
      ],
      "indexes": [
        {
          "id": "102",
          "name": "PRIMARY",
          "unique": true,
          "fieldIds": [
            "95"
          ],
          "createdAt": 1741902978198
        },
        {
          "id": "103",
          "name": "jobs_queue_index",
          "unique": false,
          "fieldIds": [
            "96"
          ],
          "createdAt": 1741902978198
        }
      ],
      "color": "#ff6b8a",
      "isView": false,
      "isMaterializedView": false,
      "createdAt": 1741902978198,
      "diagramId": "iwgpq31e7w5c"
    },
    {
      "id": "104",
      "name": "products",
      "schema": "gonza-go",
      "x": 67.85953496996788,
      "y": 61.43144196396143,
      "fields": [
        {
          "id": "105",
          "name": "id",
          "type": {
            "id": "bigint",
            "name": "bigint"
          },
          "primaryKey": true,
          "unique": true,
          "nullable": false,
          "createdAt": 1741902978199
        },
        {
          "id": "106",
          "name": "name",
          "type": {
            "id": "varchar",
            "name": "varchar"
          },
          "primaryKey": false,
          "unique": false,
          "nullable": false,
          "characterMaximumLength": "255",
          "collation": "utf8mb4_unicode_ci",
          "createdAt": 1741902978199
        },
        {
          "id": "107",
          "name": "barcode",
          "type": {
            "id": "bigint",
            "name": "bigint"
          },
          "primaryKey": false,
          "unique": true,
          "nullable": false,
          "createdAt": 1741902978199
        },
        {
          "id": "108",
          "name": "description",
          "type": {
            "id": "varchar",
            "name": "varchar"
          },
          "primaryKey": false,
          "unique": false,
          "nullable": true,
          "characterMaximumLength": "255",
          "default": "NULL",
          "collation": "utf8mb4_unicode_ci",
          "createdAt": 1741902978199
        },
        {
          "id": "109",
          "name": "price",
          "type": {
            "id": "float",
            "name": "float"
          },
          "primaryKey": false,
          "unique": false,
          "nullable": false,
          "createdAt": 1741902978199
        },
        {
          "id": "110",
          "name": "category_id",
          "type": {
            "id": "bigint",
            "name": "bigint"
          },
          "unique": false,
          "nullable": false,
          "primaryKey": false,
          "createdAt": 1741903648313
        },
        {
          "id": "111",
          "name": "created_by",
          "type": {
            "id": "bigint",
            "name": "bigint"
          },
          "unique": false,
          "nullable": false,
          "primaryKey": false,
          "createdAt": 1741902995978
        },
        {
          "id": "112",
          "name": "created_at",
          "type": {
            "id": "timestamp",
            "name": "timestamp"
          },
          "primaryKey": false,
          "unique": false,
          "nullable": true,
          "default": "NULL",
          "createdAt": 1741902978199
        },
        {
          "id": "113",
          "name": "updated_at",
          "type": {
            "id": "timestamp",
            "name": "timestamp"
          },
          "primaryKey": false,
          "unique": false,
          "nullable": true,
          "default": "NULL",
          "createdAt": 1741902978199
        }
      ],
      "indexes": [
        {
          "id": "114",
          "name": "PRIMARY",
          "unique": true,
          "fieldIds": [
            "105"
          ],
          "createdAt": 1741902978199
        },
        {
          "id": "115",
          "name": "products_barcode_unique",
          "unique": true,
          "fieldIds": [
            "107"
          ],
          "createdAt": 1741902978199
        }
      ],
      "color": "#ff6363",
      "isView": false,
      "isMaterializedView": false,
      "createdAt": 1741902978200,
      "diagramId": "iwgpq31e7w5c"
    },
    {
      "id": "116",
      "name": "orders_items",
      "x": 1195.754338630134,
      "y": 50.53053232246626,
      "fields": [
        {
          "id": "117",
          "name": "id",
          "type": {
            "id": "bigint",
            "name": "bigint"
          },
          "unique": true,
          "nullable": false,
          "primaryKey": true,
          "createdAt": 1741905532683
        },
        {
          "id": "118",
          "name": "order_id",
          "type": {
            "id": "bigint",
            "name": "bigint"
          },
          "unique": false,
          "nullable": false,
          "primaryKey": false,
          "createdAt": 1741905558555
        },
        {
          "id": "119",
          "name": "product_id",
          "type": {
            "id": "bigint",
            "name": "bigint"
          },
          "unique": false,
          "nullable": false,
          "primaryKey": false,
          "createdAt": 1741905691320
        },
        {
          "id": "120",
          "name": "quantity",
          "type": {
            "id": "int",
            "name": "int"
          },
          "unique": false,
          "nullable": false,
          "primaryKey": false,
          "createdAt": 1741905727497
        },
        {
          "id": "121",
          "name": "price",
          "type": {
            "id": "float",
            "name": "float"
          },
          "unique": false,
          "nullable": false,
          "primaryKey": false,
          "createdAt": 1741905754251
        }
      ],
      "indexes": [],
      "color": "#4dee8a",
      "createdAt": 1741905532683,
      "isView": false,
      "order": 18,
      "diagramId": "iwgpq31e7w5c"
    },
    {
      "id": "122",
      "name": "product_details",
      "x": -352.698487138532,
      "y": 146.46970660705492,
      "fields": [
        {
          "id": "123",
          "name": "id",
          "type": {
            "id": "bigint",
            "name": "bigint"
          },
          "unique": true,
          "nullable": false,
          "primaryKey": true,
          "createdAt": 1750015836488
        },
        {
          "id": "124",
          "name": "product_id",
          "type": {
            "id": "bigint",
            "name": "bigint"
          },
          "unique": false,
          "nullable": false,
          "primaryKey": false,
          "createdAt": 1750015523257
        },
        {
          "id": "125",
          "name": "detail_id",
          "type": {
            "id": "bigint",
            "name": "bigint"
          },
          "unique": false,
          "nullable": false,
          "primaryKey": false,
          "createdAt": 1750015735559
        },
        {
          "id": "126",
          "name": "value",
          "type": {
            "id": "text",
            "name": "text"
          },
          "unique": false,
          "nullable": false,
          "primaryKey": false,
          "createdAt": 1750015796426
        }
      ],
      "indexes": [],
      "color": "#42e0c0",
      "createdAt": 1750015523257,
      "isView": false,
      "order": 28,
      "diagramId": "iwgpq31e7w5c"
    },
    {
      "id": "127",
      "name": "cache_locks",
      "schema": "gonza-go",
      "x": 450.129722024234,
      "y": 989.7739130434779,
      "fields": [
        {
          "id": "128",
          "name": "key",
          "type": {
            "id": "varchar",
            "name": "varchar"
          },
          "primaryKey": true,
          "unique": true,
          "nullable": false,
          "characterMaximumLength": "255",
          "collation": "utf8mb4_unicode_ci",
          "createdAt": 1741902978199
        },
        {
          "id": "129",
          "name": "owner",
          "type": {
            "id": "varchar",
            "name": "varchar"
          },
          "primaryKey": false,
          "unique": false,
          "nullable": false,
          "characterMaximumLength": "255",
          "collation": "utf8mb4_unicode_ci",
          "createdAt": 1741902978199
        },
        {
          "id": "130",
          "name": "expiration",
          "type": {
            "id": "int",
            "name": "int"
          },
          "primaryKey": false,
          "unique": false,
          "nullable": false,
          "createdAt": 1741902978199
        }
      ],
      "indexes": [
        {
          "id": "131",
          "name": "PRIMARY",
          "unique": true,
          "fieldIds": [
            "128"
          ],
          "createdAt": 1741902978199
        }
      ],
      "color": "#ff6363",
      "isView": false,
      "isMaterializedView": false,
      "createdAt": 1741902978199,
      "diagramId": "iwgpq31e7w5c"
    },
    {
      "id": "132",
      "name": "users",
      "schema": "gonza-go",
      "x": 485.85819538678584,
      "y": -372.17858492479894,
      "fields": [
        {
          "id": "133",
          "name": "id",
          "type": {
            "id": "bigint",
            "name": "bigint"
          },
          "primaryKey": true,
          "unique": true,
          "nullable": false,
          "createdAt": 1741902978198
        },
        {
          "id": "134",
          "name": "name",
          "type": {
            "id": "varchar",
            "name": "varchar"
          },
          "primaryKey": false,
          "unique": false,
          "nullable": false,
          "characterMaximumLength": "255",
          "collation": "utf8mb4_unicode_ci",
          "createdAt": 1741902978198
        },
        {
          "id": "135",
          "name": "email",
          "type": {
            "id": "varchar",
            "name": "varchar"
          },
          "primaryKey": false,
          "unique": true,
          "nullable": false,
          "characterMaximumLength": "255",
          "collation": "utf8mb4_unicode_ci",
          "createdAt": 1741902978198
        },
        {
          "id": "136",
          "name": "email_verified_at",
          "type": {
            "id": "timestamp",
            "name": "timestamp"
          },
          "primaryKey": false,
          "unique": false,
          "nullable": true,
          "default": "NULL",
          "createdAt": 1741902978198
        },
        {
          "id": "137",
          "name": "password",
          "type": {
            "id": "varchar",
            "name": "varchar"
          },
          "primaryKey": false,
          "unique": false,
          "nullable": false,
          "characterMaximumLength": "255",
          "collation": "utf8mb4_unicode_ci",
          "createdAt": 1741902978198
        },
        {
          "id": "138",
          "name": "remember_token",
          "type": {
            "id": "varchar",
            "name": "varchar"
          },
          "primaryKey": false,
          "unique": false,
          "nullable": true,
          "characterMaximumLength": "100",
          "default": "NULL",
          "collation": "utf8mb4_unicode_ci",
          "createdAt": 1741902978198
        },
        {
          "id": "139",
          "name": "created_at",
          "type": {
            "id": "timestamp",
            "name": "timestamp"
          },
          "primaryKey": false,
          "unique": false,
          "nullable": true,
          "default": "NULL",
          "createdAt": 1741902978198
        },
        {
          "id": "140",
          "name": "updated_at",
          "type": {
            "id": "timestamp",
            "name": "timestamp"
          },
          "primaryKey": false,
          "unique": false,
          "nullable": true,
          "default": "NULL",
          "createdAt": 1741902978198
        }
      ],
      "indexes": [
        {
          "id": "141",
          "name": "PRIMARY",
          "unique": true,
          "fieldIds": [
            "133"
          ],
          "createdAt": 1741902978198
        },
        {
          "id": "142",
          "name": "users_email_unique",
          "unique": true,
          "fieldIds": [
            "135"
          ],
          "createdAt": 1741902978198
        }
      ],
      "color": "#ffe374",
      "isView": false,
      "isMaterializedView": false,
      "createdAt": 1741902978198,
      "diagramId": "iwgpq31e7w5c"
    },
    {
      "id": "143",
      "name": "supplier_order",
      "x": -347.8364600122599,
      "y": -155.77997035508105,
      "fields": [
        {
          "id": "144",
          "name": "id",
          "type": {
            "id": "bigint",
            "name": "bigint"
          },
          "unique": true,
          "nullable": false,
          "primaryKey": true,
          "createdAt": 1744990938116
        },
        {
          "id": "145",
          "name": "supplier_id",
          "type": {
            "id": "bigint",
            "name": "bigint"
          },
          "unique": false,
          "nullable": false,
          "primaryKey": false,
          "createdAt": 1744990980556
        },
        {
          "id": "146",
          "name": "total",
          "type": {
            "id": "decimal",
            "name": "decimal"
          },
          "unique": false,
          "nullable": false,
          "primaryKey": false,
          "createdAt": 1744991561018
        },
        {
          "id": "147",
          "name": "note",
          "type": {
            "id": "varchar",
            "name": "varchar"
          },
          "unique": false,
          "nullable": true,
          "primaryKey": false,
          "createdAt": 1744991538689
        },
        {
          "id": "148",
          "name": "created_at",
          "type": {
            "id": "timestamp",
            "name": "timestamp"
          },
          "unique": false,
          "nullable": true,
          "primaryKey": false,
          "createdAt": 1744991004698
        },
        {
          "id": "149",
          "name": "updated_at",
          "type": {
            "id": "timestamp",
            "name": "timestamp"
          },
          "unique": false,
          "nullable": true,
          "primaryKey": false,
          "createdAt": 1744991020084
        }
      ],
      "indexes": [],
      "color": "#4dee8a",
      "createdAt": 1744990938116,
      "isView": false,
      "order": 21,
      "diagramId": "iwgpq31e7w5c"
    },
    {
      "id": "150",
      "name": "inventory",
      "x": -256.2889675591563,
      "y": 378.979236460679,
      "fields": [
        {
          "id": "151",
          "name": "id",
          "type": {
            "id": "bigint",
            "name": "bigint"
          },
          "unique": true,
          "nullable": false,
          "primaryKey": true,
          "createdAt": 1741905920728
        },
        {
          "id": "152",
          "name": "product_id",
          "type": {
            "id": "bigint",
            "name": "bigint"
          },
          "unique": false,
          "nullable": false,
          "primaryKey": false,
          "createdAt": 1741905977734
        },
        {
          "id": "153",
          "name": "quantity",
          "type": {
            "id": "int",
            "name": "int"
          },
          "unique": false,
          "nullable": false,
          "primaryKey": false,
          "createdAt": 1741906038597
        }
      ],
      "indexes": [],
      "color": "#7175fa",
      "createdAt": 1741905920728,
      "isView": false,
      "order": 19,
      "diagramId": "iwgpq31e7w5c"
    },
    {
      "id": "154",
      "name": "details",
      "x": -648.4007168818812,
      "y": 240.33226357028792,
      "fields": [
        {
          "id": "155",
          "name": "id",
          "type": {
            "id": "bigint",
            "name": "bigint"
          },
          "unique": true,
          "nullable": false,
          "primaryKey": true,
          "createdAt": 1750015956537
        },
        {
          "id": "156",
          "name": "name",
          "type": {
            "id": "text",
            "name": "text"
          },
          "unique": false,
          "nullable": false,
          "primaryKey": false,
          "createdAt": 1750016015922
        },
        {
          "id": "157",
          "name": "type",
          "type": {
            "id": "enum",
            "name": "enum"
          },
          "unique": false,
          "nullable": false,
          "primaryKey": false,
          "createdAt": 1750015976195
        }
      ],
      "indexes": [],
      "color": "#9ef07a",
      "createdAt": 1750015956537,
      "isView": false,
      "order": 29,
      "diagramId": "iwgpq31e7w5c"
    },
    {
      "id": "158",
      "name": "supplier_order_receive",
      "x": -959.4216493861194,
      "y": 12.572384593936183,
      "fields": [
        {
          "id": "159",
          "name": "id",
          "type": {
            "id": "bigint",
            "name": "bigint"
          },
          "unique": true,
          "nullable": false,
          "primaryKey": true,
          "createdAt": 1744992138368
        },
        {
          "id": "160",
          "name": "item_id",
          "type": {
            "id": "bigint",
            "name": "bigint"
          },
          "unique": false,
          "nullable": false,
          "primaryKey": false,
          "createdAt": 1744992194601
        },
        {
          "id": "161",
          "name": "quantity",
          "type": {
            "id": "int",
            "name": "int"
          },
          "unique": false,
          "nullable": false,
          "primaryKey": false,
          "createdAt": 1744992224729
        },
        {
          "id": "162",
          "name": "date",
          "type": {
            "id": "timestamp",
            "name": "timestamp"
          },
          "unique": false,
          "nullable": true,
          "primaryKey": false,
          "createdAt": 1744992317843
        }
      ],
      "indexes": [],
      "color": "#b067e9",
      "createdAt": 1744992138368,
      "isView": false,
      "order": 25,
      "diagramId": "iwgpq31e7w5c"
    },
    {
      "id": "163",
      "name": "product_images",
      "x": -211.84881830451175,
      "y": 626.8628597799133,
      "fields": [
        {
          "id": "164",
          "name": "id",
          "type": {
            "id": "bigint",
            "name": "bigint"
          },
          "unique": true,
          "nullable": false,
          "primaryKey": true,
          "createdAt": 1741904016916
        },
        {
          "id": "165",
          "name": "product_id",
          "type": {
            "id": "bigint",
            "name": "bigint"
          },
          "unique": false,
          "nullable": false,
          "primaryKey": false,
          "createdAt": 1741904086053
        },
        {
          "id": "166",
          "name": "image",
          "type": {
            "id": "varchar",
            "name": "varchar"
          },
          "unique": false,
          "nullable": false,
          "primaryKey": false,
          "createdAt": 1741904120429,
          "characterMaximumLength": "256"
        },
        {
          "id": "167",
          "name": "is_primary",
          "type": {
            "id": "bool",
            "name": "bool"
          },
          "unique": false,
          "nullable": false,
          "primaryKey": false,
          "createdAt": 1741904376714
        }
      ],
      "indexes": [],
      "color": "#9ef07a",
      "createdAt": 1741904016916,
      "isView": false,
      "order": 16,
      "diagramId": "iwgpq31e7w5c"
    },
    {
      "id": "168",
      "name": "supplier_order_status",
      "x": -652.330152437476,
      "y": -306.03566855205315,
      "fields": [
        {
          "id": "169",
          "name": "id",
          "type": {
            "id": "bigint",
            "name": "bigint"
          },
          "unique": true,
          "nullable": false,
          "primaryKey": true,
          "createdAt": 1744991958406
        },
        {
          "id": "170",
          "name": "order_id",
          "type": {
            "id": "bigint",
            "name": "bigint"
          },
          "unique": false,
          "nullable": false,
          "primaryKey": false,
          "createdAt": 1744991992390
        },
        {
          "id": "171",
          "name": "status",
          "type": {
            "id": "enum",
            "name": "enum"
          },
          "unique": false,
          "nullable": false,
          "primaryKey": false,
          "createdAt": 1744992017031
        },
        {
          "id": "172",
          "name": "date",
          "type": {
            "id": "timestamp",
            "name": "timestamp"
          },
          "unique": false,
          "nullable": false,
          "primaryKey": false,
          "createdAt": 1744992035255
        }
      ],
      "indexes": [],
      "color": "#9ef07a",
      "createdAt": 1744991958406,
      "isView": false,
      "order": 24,
      "diagramId": "iwgpq31e7w5c"
    },
    {
      "id": "173",
      "name": "supplier_order_items",
      "x": -657.7318254879328,
      "y": -28.782085846374578,
      "fields": [
        {
          "id": "174",
          "name": "id",
          "type": {
            "id": "bigint",
            "name": "bigint"
          },
          "unique": true,
          "nullable": false,
          "primaryKey": true,
          "createdAt": 1744991702130
        },
        {
          "id": "175",
          "name": "order_id",
          "type": {
            "id": "bigint",
            "name": "bigint"
          },
          "unique": false,
          "nullable": false,
          "primaryKey": false,
          "createdAt": 1744991727605
        },
        {
          "id": "176",
          "name": "product_id",
          "type": {
            "id": "bigint",
            "name": "bigint"
          },
          "unique": false,
          "nullable": false,
          "primaryKey": false,
          "createdAt": 1744991770028
        },
        {
          "id": "177",
          "name": "quantity",
          "type": {
            "id": "int",
            "name": "int"
          },
          "unique": false,
          "nullable": false,
          "primaryKey": false,
          "createdAt": 1744991823237
        },
        {
          "id": "178",
          "name": "unit_price",
          "type": {
            "id": "decimal",
            "name": "decimal"
          },
          "unique": false,
          "nullable": false,
          "primaryKey": false,
          "createdAt": 1744991847814
        },
        {
          "id": "179",
          "name": "subtotal",
          "type": {
            "id": "decimal",
            "name": "decimal"
          },
          "unique": false,
          "nullable": false,
          "primaryKey": false,
          "createdAt": 1744991890246
        }
      ],
      "indexes": [],
      "color": "#ffe374",
      "createdAt": 1744991702130,
      "isView": false,
      "order": 23,
      "diagramId": "iwgpq31e7w5c"
    },
    {
      "id": "180",
      "name": "job_batches",
      "schema": "gonza-go",
      "x": -205.26129722024262,
      "y": 887.2359230220952,
      "fields": [
        {
          "id": "181",
          "name": "id",
          "type": {
            "id": "varchar",
            "name": "varchar"
          },
          "primaryKey": true,
          "unique": true,
          "nullable": false,
          "characterMaximumLength": "255",
          "collation": "utf8mb4_unicode_ci",
          "createdAt": 1741902978197
        },
        {
          "id": "182",
          "name": "name",
          "type": {
            "id": "varchar",
            "name": "varchar"
          },
          "primaryKey": false,
          "unique": false,
          "nullable": false,
          "characterMaximumLength": "255",
          "collation": "utf8mb4_unicode_ci",
          "createdAt": 1741902978197
        },
        {
          "id": "183",
          "name": "total_jobs",
          "type": {
            "id": "int",
            "name": "int"
          },
          "primaryKey": false,
          "unique": false,
          "nullable": false,
          "createdAt": 1741902978197
        },
        {
          "id": "184",
          "name": "pending_jobs",
          "type": {
            "id": "int",
            "name": "int"
          },
          "primaryKey": false,
          "unique": false,
          "nullable": false,
          "createdAt": 1741902978197
        },
        {
          "id": "185",
          "name": "failed_jobs",
          "type": {
            "id": "int",
            "name": "int"
          },
          "primaryKey": false,
          "unique": false,
          "nullable": false,
          "createdAt": 1741902978197
        },
        {
          "id": "186",
          "name": "failed_job_ids",
          "type": {
            "id": "longtext",
            "name": "longtext"
          },
          "primaryKey": false,
          "unique": false,
          "nullable": false,
          "characterMaximumLength": "4294967295",
          "collation": "utf8mb4_unicode_ci",
          "createdAt": 1741902978197
        },
        {
          "id": "187",
          "name": "options",
          "type": {
            "id": "mediumtext",
            "name": "mediumtext"
          },
          "primaryKey": false,
          "unique": false,
          "nullable": true,
          "characterMaximumLength": "16777215",
          "default": "NULL",
          "collation": "utf8mb4_unicode_ci",
          "createdAt": 1741902978198
        },
        {
          "id": "188",
          "name": "cancelled_at",
          "type": {
            "id": "int",
            "name": "int"
          },
          "primaryKey": false,
          "unique": false,
          "nullable": true,
          "default": "NULL",
          "createdAt": 1741902978198
        },
        {
          "id": "189",
          "name": "created_at",
          "type": {
            "id": "int",
            "name": "int"
          },
          "primaryKey": false,
          "unique": false,
          "nullable": false,
          "createdAt": 1741902978198
        },
        {
          "id": "190",
          "name": "finished_at",
          "type": {
            "id": "int",
            "name": "int"
          },
          "primaryKey": false,
          "unique": false,
          "nullable": true,
          "default": "NULL",
          "createdAt": 1741902978198
        }
      ],
      "indexes": [
        {
          "id": "191",
          "name": "PRIMARY",
          "unique": true,
          "fieldIds": [
            "181"
          ],
          "createdAt": 1741902978198
        }
      ],
      "color": "#ffe374",
      "isView": false,
      "isMaterializedView": false,
      "createdAt": 1741902978198,
      "diagramId": "iwgpq31e7w5c"
    },
    {
      "id": "192",
      "name": "model_has_permissions",
      "schema": "gonza-go",
      "x": 1300,
      "y": 550,
      "fields": [
        {
          "id": "193",
          "name": "permission_id",
          "type": {
            "id": "bigint",
            "name": "bigint"
          },
          "primaryKey": true,
          "unique": false,
          "nullable": false,
          "createdAt": 1741902978199
        },
        {
          "id": "194",
          "name": "model_type",
          "type": {
            "id": "varchar",
            "name": "varchar"
          },
          "primaryKey": true,
          "unique": false,
          "nullable": false,
          "characterMaximumLength": "255",
          "collation": "utf8mb4_unicode_ci",
          "createdAt": 1741902978199
        },
        {
          "id": "195",
          "name": "model_id",
          "type": {
            "id": "bigint",
            "name": "bigint"
          },
          "primaryKey": true,
          "unique": false,
          "nullable": false,
          "createdAt": 1741902978199
        }
      ],
      "indexes": [
        {
          "id": "196",
          "name": "PRIMARY",
          "unique": true,
          "fieldIds": [
            "193",
            "195",
            "194"
          ],
          "createdAt": 1741902978199
        },
        {
          "id": "197",
          "name": "model_has_permissions_model_id_model_type_index",
          "unique": false,
          "fieldIds": [
            "195",
            "194"
          ],
          "createdAt": 1741902978199
        }
      ],
      "color": "#8a61f5",
      "isView": false,
      "isMaterializedView": false,
      "createdAt": 1741902978199,
      "diagramId": "iwgpq31e7w5c"
    }
  ],
  "relationships": [
    {
      "id": "198",
      "name": "brands_created_by_fk",
      "sourceTableId": "9",
      "targetTableId": "132",
      "sourceFieldId": "12",
      "targetFieldId": "133",
      "sourceCardinality": "one",
      "targetCardinality": "one",
      "createdAt": 1750014365111,
      "diagramId": "iwgpq31e7w5c"
    },
    {
      "id": "199",
      "name": "details_id_fk",
      "sourceTableId": "154",
      "targetTableId": "122",
      "sourceFieldId": "155",
      "targetFieldId": "125",
      "sourceCardinality": "one",
      "targetCardinality": "many",
      "createdAt": 1750015972618,
      "diagramId": "iwgpq31e7w5c"
    },
    {
      "id": "200",
      "name": "model_has_permissions_permission_id_foreign",
      "sourceSchema": "gonza-go",
      "targetSchema": "gonza-go",
      "sourceTableId": "192",
      "targetTableId": "44",
      "sourceFieldId": "193",
      "targetFieldId": "45",
      "sourceCardinality": "many",
      "targetCardinality": "one",
      "createdAt": 1741902978201,
      "diagramId": "iwgpq31e7w5c"
    },
    {
      "id": "201",
      "name": "model_has_roles_role_id_foreign",
      "sourceSchema": "gonza-go",
      "targetSchema": "gonza-go",
      "sourceTableId": "23",
      "targetTableId": "86",
      "sourceFieldId": "24",
      "targetFieldId": "87",
      "sourceCardinality": "many",
      "targetCardinality": "one",
      "createdAt": 1741902978201,
      "diagramId": "iwgpq31e7w5c"
    },
    {
      "id": "202",
      "name": "orders_id_fk",
      "sourceTableId": "52",
      "targetTableId": "116",
      "sourceFieldId": "53",
      "targetFieldId": "118",
      "sourceCardinality": "one",
      "targetCardinality": "many",
      "createdAt": 1741905881952,
      "diagramId": "iwgpq31e7w5c"
    },
    {
      "id": "203",
      "name": "orders_items_product_id_fk",
      "sourceTableId": "116",
      "targetTableId": "104",
      "sourceFieldId": "119",
      "targetFieldId": "105",
      "sourceCardinality": "one",
      "targetCardinality": "one",
      "createdAt": 1741905707610,
      "diagramId": "iwgpq31e7w5c"
    },
    {
      "id": "204",
      "name": "orders_user_id_fk",
      "sourceTableId": "52",
      "targetTableId": "132",
      "sourceFieldId": "54",
      "targetFieldId": "133",
      "sourceCardinality": "many",
      "targetCardinality": "one",
      "createdAt": 1741905190276,
      "diagramId": "iwgpq31e7w5c"
    },
    {
      "id": "205",
      "name": "product_brands_brand_id_fk",
      "sourceTableId": "64",
      "targetTableId": "9",
      "sourceFieldId": "66",
      "targetFieldId": "10",
      "sourceCardinality": "many",
      "targetCardinality": "one",
      "createdAt": 1750014457582,
      "diagramId": "iwgpq31e7w5c"
    },
    {
      "id": "206",
      "name": "product_details_product_id_fk",
      "sourceTableId": "122",
      "targetTableId": "104",
      "sourceFieldId": "124",
      "targetFieldId": "105",
      "sourceCardinality": "one",
      "targetCardinality": "one",
      "createdAt": 1750015616019,
      "diagramId": "iwgpq31e7w5c"
    },
    {
      "id": "207",
      "name": "product_images_product_id_fk",
      "sourceTableId": "163",
      "targetTableId": "104",
      "sourceFieldId": "165",
      "targetFieldId": "105",
      "sourceCardinality": "many",
      "targetCardinality": "one",
      "createdAt": 1741904106709,
      "diagramId": "iwgpq31e7w5c"
    },
    {
      "id": "208",
      "name": "products_category_id_fk",
      "sourceSchema": "gonza-go",
      "sourceTableId": "104",
      "targetSchema": "gonza-go",
      "targetTableId": "67",
      "sourceFieldId": "110",
      "targetFieldId": "68",
      "sourceCardinality": "many",
      "targetCardinality": "one",
      "createdAt": 1741903718679,
      "diagramId": "iwgpq31e7w5c"
    },
    {
      "id": "209",
      "name": "products_created_by_fk",
      "sourceSchema": "gonza-go",
      "sourceTableId": "104",
      "targetSchema": "gonza-go",
      "targetTableId": "132",
      "sourceFieldId": "111",
      "targetFieldId": "133",
      "sourceCardinality": "one",
      "targetCardinality": "one",
      "createdAt": 1741903036266,
      "diagramId": "iwgpq31e7w5c"
    },
    {
      "id": "210",
      "name": "products_id_fk",
      "sourceSchema": "gonza-go",
      "sourceTableId": "104",
      "targetSchema": "gonza-go",
      "targetTableId": "64",
      "sourceFieldId": "105",
      "targetFieldId": "65",
      "sourceCardinality": "one",
      "targetCardinality": "one",
      "createdAt": 1750014447040,
      "diagramId": "iwgpq31e7w5c"
    },
    {
      "id": "211",
      "name": "products_id_fk",
      "sourceSchema": "gonza-go",
      "sourceTableId": "104",
      "targetSchema": "gonza-go",
      "targetTableId": "150",
      "sourceFieldId": "105",
      "targetFieldId": "152",
      "sourceCardinality": "one",
      "targetCardinality": "one",
      "createdAt": 1741906026037,
      "diagramId": "iwgpq31e7w5c"
    },
    {
      "id": "213",
      "name": "role_has_permissions_permission_id_foreign",
      "sourceSchema": "gonza-go",
      "targetSchema": "gonza-go",
      "sourceTableId": "81",
      "targetTableId": "44",
      "sourceFieldId": "82",
      "targetFieldId": "45",
      "sourceCardinality": "many",
      "targetCardinality": "one",
      "createdAt": 1741902978201,
      "diagramId": "iwgpq31e7w5c"
    },
    {
      "id": "214",
      "name": "role_has_permissions_role_id_foreign",
      "sourceSchema": "gonza-go",
      "targetSchema": "gonza-go",
      "sourceTableId": "81",
      "targetTableId": "86",
      "sourceFieldId": "83",
      "targetFieldId": "87",
      "sourceCardinality": "many",
      "targetCardinality": "one",
      "createdAt": 1741902978201,
      "diagramId": "iwgpq31e7w5c"
    },
    {
      "id": "215",
      "name": "supplier_contacts_supplier_id_fk",
      "sourceTableId": "58",
      "targetTableId": "1",
      "sourceFieldId": "60",
      "targetFieldId": "2",
      "sourceCardinality": "one",
      "targetCardinality": "one",
      "createdAt": 1744991281394,
      "diagramId": "iwgpq31e7w5c"
    },
    {
      "id": "216",
      "name": "supplier_order_items_order_id_fk",
      "sourceTableId": "173",
      "targetTableId": "143",
      "sourceFieldId": "175",
      "targetFieldId": "144",
      "sourceCardinality": "one",
      "targetCardinality": "one",
      "createdAt": 1744991740580,
      "diagramId": "iwgpq31e7w5c"
    },
    {
      "id": "217",
      "name": "supplier_order_items_product_id_fk",
      "sourceTableId": "173",
      "targetTableId": "104",
      "sourceFieldId": "176",
      "targetFieldId": "105",
      "sourceCardinality": "one",
      "targetCardinality": "one",
      "createdAt": 1744991793548,
      "diagramId": "iwgpq31e7w5c"
    },
    {
      "id": "218",
      "name": "supplier_order_receive_item_id_fk",
      "sourceTableId": "158",
      "targetTableId": "173",
      "sourceFieldId": "160",
      "targetFieldId": "174",
      "sourceCardinality": "one",
      "targetCardinality": "one",
      "createdAt": 1744992289370,
      "diagramId": "iwgpq31e7w5c"
    },
    {
      "id": "219",
      "name": "supplier_order_status_order_id_fk",
      "sourceTableId": "168",
      "targetTableId": "143",
      "sourceFieldId": "170",
      "targetFieldId": "144",
      "sourceCardinality": "one",
      "targetCardinality": "one",
      "createdAt": 1744992004365,
      "diagramId": "iwgpq31e7w5c"
    },
    {
      "id": "220",
      "name": "supplier_order_supplier_id_fk",
      "sourceTableId": "143",
      "targetTableId": "1",
      "sourceFieldId": "145",
      "targetFieldId": "2",
      "sourceCardinality": "one",
      "targetCardinality": "one",
      "createdAt": 1744990994083,
      "diagramId": "iwgpq31e7w5c"
    },
    {
      "id": "221",
      "name": "suppliers_created_by_fk",
      "sourceTableId": "1",
      "targetTableId": "132",
      "sourceFieldId": "6",
      "targetFieldId": "133",
      "sourceCardinality": "one",
      "targetCardinality": "one",
      "createdAt": 1744990485872,
      "diagramId": "iwgpq31e7w5c"
    }
  ],
  "dependencies": [],
  "areas": [],
  "customTypes": []
}